Metadata-Version: 2.1
Name: hello_cr1sk_world_lib
Version: 0.1
Summary: A simple library that prints 'Hello, World!'
Home-page: https://github.com/gabrfern99/hello_cr1sk_world_lib
Author: Gabriel
Author-email: gabr.fern99@gmail.com
Classifier: Programming Language :: Python :: 3
Classifier: License :: OSI Approved :: MIT License
Classifier: Operating System :: OS Independent
Requires-Python: >=3.6
